{"cameraMode":{"drawMode":0,"name":"Shaded","section":"Shading Mode"},"sceneLighting":true,"audioPlay":false,"sceneViewState":{"showFog":true,"showMaterialUpdate":false,"showSkybox":true,"showFlares":true,"showImageEffects":true,"showParticleSystems":true},"in2DMode":false,"pivot":{"x":10.293904304504395,"y":1.0968351364135743,"z":18.815767288208009},"rotation":{"x":-0.027305280789732934,"y":-0.20749488472938538,"z":0.005792609415948391,"w":-0.9778378009796143},"size":9.157023429870606,"orthographic":false}